langdetect_zh/__init__.py
langdetect_zh/detector.py
langdetect_zh/detector_factory.py
langdetect_zh/lang_detect_exception.py
langdetect_zh/language.py
langdetect_zh/profiles/zh-cn
langdetect_zh/profiles/zh-tw
langdetect_zh/tests/__init__.py
langdetect_zh/tests/test_detector.py
langdetect_zh/tests/test_language.py
langdetect_zh/utils/__init__.py
langdetect_zh/utils/lang_profile.py
langdetect_zh/utils/messages.properties
langdetect_zh/utils/messages.py
langdetect_zh/utils/ngram.py
langdetect_zh/utils/unicode_block.py
langdetect_zh-1.0.4.dist-info/licenses/LICENSE
langdetect_zh-1.0.4.dist-info/METADATA
langdetect_zh-1.0.4.dist-info/WHEEL
langdetect_zh-1.0.4.dist-info/top_level.txt
langdetect_zh-1.0.4.dist-info/RECORD
